{"segments": [{"start": 1147, "end": 2050, "text": "\u4e00\u70b9\u4e94"}, {"start": 3331, "end": 5452, "text": "\u8ddf \u8bfb \u4e0b\u9762 \u7684 \u8bcd\u8bed"}, {"start": 6524, "end": 7226, "text": "\u54ce"}, {"start": 8882, "end": 9565, "text": "\u4e00"}, {"start": 10394, "end": 11732, "text": "\u53bb \u5929\u6d25"}, {"start": 13248, "end": 13936, "text": "\u4e8c"}, {"start": 14759, "end": 15984, "text": "\u67e5 \u8bcd\u5178"}, {"start": 18117, "end": 18837, "text": "\u4e09"}, {"start": 19508, "end": 20869, "text": "\u53bb \u5e7f\u5dde"}, {"start": 22398, "end": 23034, "text": "\u56db"}, {"start": 23816, "end": 25133, "text": "\u5403\u9971 \u4e86"}, {"start": 27164, "end": 28029, "text": "\u4e94"}, {"start": 28981, "end": 30283, "text": "\u670d\u88c5\u5e97"}, {"start": 31518, "end": 32210, "text": "\u6599"}, {"start": 33159, "end": 34435, "text": "\u6559\u7814\u5ba4"}, {"start": 36816, "end": 37430, "text": "\u6bd5"}, {"start": 38229, "end": 38888, "text": "\u4e03"}, {"start": 39629, "end": 41236, "text": "\u63d0\u9ad8 \u6c34\u5e73"}, {"start": 43142, "end": 43873, "text": "\u516b"}, {"start": 44779, "end": 46456, "text": "\u4e0b\u8bfe \u4ee5\u540e"}, {"start": 48655, "end": 49545, "text": "\u811a"}, {"start": 50205, "end": 51860, "text": "\u4e0a\u8bfe \u4ee5\u524d"}, {"start": 52789, "end": 53526, "text": "\u4e60"}, {"start": 54322, "end": 55944, "text": "\u73b0\u5728 \u51e0\u70b9"}, {"start": 57903, "end": 58701, "text": "\u5341 \u4e00"}, {"start": 59318, "end": 60791, "text": "\u5154\u5b50 \u8dd1 \u4e86"}, {"start": 62140, "end": 62994, "text": "\u5341 \u4e8c"}, {"start": 63834, "end": 65488, "text": "\u809a\u5b50 \u9971 \u4e86"}, {"start": 66956, "end": 70035, "text": "\u5341 \u4e09 \u53e4\u5178\u6587\u5b66"}, {"start": 71227, "end": 72023, "text": "\u5341 \u56db"}, {"start": 72747, "end": 74523, "text": "\u51e0\u6708 \u51e0\u53f7"}]}